content_hash/__init__.py
content_hash/__main__.py
content_hash/utils.py
content_hash/decodes/__init__.py
content_hash/decodes/b58_multi_hash.py
content_hash/decodes/hex_multi_hash.py
content_hash/decodes/utf8.py
content_hash/encodes/__init__.py
content_hash/encodes/ipfs.py
content_hash/encodes/swarm.py
content_hash/encodes/utf8.py
content_hash/profiles/__init__.py
rotki_content_hash-0.0.3.dist-info/LICENSE
rotki_content_hash-0.0.3.dist-info/METADATA
rotki_content_hash-0.0.3.dist-info/WHEEL
rotki_content_hash-0.0.3.dist-info/entry_points.txt
rotki_content_hash-0.0.3.dist-info/top_level.txt
rotki_content_hash-0.0.3.dist-info/RECORD
