Metadata-Version: 2.1
Name: rotki-content-hash
Version: 0.0.3
Summary: Python implementation of EIP 1577 content hash
Home-page: https://github.com/filips123/ContentHashPy/
Author: Filip Š
Author-email: projects@filips.si
License: MIT
Keywords: ethereum,ethereum-name-service,ens,eip1577,web3,decentralized
Classifier: Development Status :: 5 - Production/Stable
Classifier: Intended Audience :: Developers
Classifier: License :: OSI Approved :: MIT License
Classifier: Programming Language :: Python :: 3
Classifier: Topic :: Internet :: Name Service (DNS)
Classifier: Topic :: Scientific/Engineering :: Interface Engine/Protocol Translator
Classifier: Topic :: Security :: Cryptography
Classifier: Topic :: Software Development :: Libraries
Classifier: Topic :: Utilities
Requires-Python: >= 3.5
License-File: LICENSE
Requires-Dist: multiformats
Requires-Dist: base58check
Requires-Dist: pysha3
Requires-Dist: typing-extensions (==4.5.0)
Provides-Extra: lint
Requires-Dist: pylint ; extra == 'lint'
Provides-Extra: test
Requires-Dist: pytest ; extra == 'test'
Requires-Dist: pytest-cov ; extra == 'test'
